MANIFEST.in
README.rst
flask_googleauth.py
setup.py
Flask_GoogleAuth.egg-info/PKG-INFO
Flask_GoogleAuth.egg-info/SOURCES.txt
Flask_GoogleAuth.egg-info/dependency_links.txt
Flask_GoogleAuth.egg-info/not-zip-safe
Flask_GoogleAuth.egg-info/requires.txt
Flask_GoogleAuth.egg-info/top_level.txt