Metadata-Version: 1.1
Name: Flask-GoogleAuth
Version: 0.4
Summary: Super simple OpenID and Google Federated Auth for Flask apps.
Home-page: https://github.com/sashka/flask-googleauth
Author: Alexander Saltanov
Author-email: asd@mokote.com
License: BSD
Platform: any
Classifier: Environment :: Web Environment
Classifier: Intended Audience :: Developers
Classifier: License :: OSI Approved :: BSD License
Classifier: Operating System :: OS Independent
Classifier: Programming Language :: Python
Classifier: Topic :: Internet :: WWW/HTTP :: Dynamic Content
Classifier: Topic :: Software Development :: Libraries :: Python Modules
